Metadata-Version: 1.0
Name: mssecret
Version: 0.1
Summary: Mommy's Secret
Home-page: https://github.com/fxie97/python-packaging-template
Author: fxie97
Author-email: jinse18@gmail.com
License: MIT
Platform: UNKNOWN
